email_validator/__init__.py
email_validator/test.py
email_validator_vector_friendly-1.1.4.dist-info/LICENSE
email_validator_vector_friendly-1.1.4.dist-info/METADATA
email_validator_vector_friendly-1.1.4.dist-info/WHEEL
email_validator_vector_friendly-1.1.4.dist-info/entry_points.txt
email_validator_vector_friendly-1.1.4.dist-info/top_level.txt
email_validator_vector_friendly-1.1.4.dist-info/RECORD
