Metadata-Version: 2.1
Name: email-validator-vector-friendly
Version: 1.1.4
Summary: A robust email syntax and deliverability validation library for Python 2.x/3.x forked for vectorization
Home-page: https://github.com/bmerrill17/python-email-validator
Author: Bryce Merrill
Author-email: brycelmerrill@gmail.com
License: CC0 (copyright waived)
Keywords: email address validator
Platform: UNKNOWN
Classifier: Development Status :: 5 - Production/Stable
Classifier: Intended Audience :: Developers
Classifier: License :: CC0 1.0 Universal (CC0 1.0) Public Domain Dedication
Classifier: Programming Language :: Python :: 2
Classifier: Programming Language :: Python :: 2.7
Classifier: Programming Language :: Python :: 3
Classifier: Programming Language :: Python :: 3.5
Classifier: Programming Language :: Python :: 3.6
Classifier: Programming Language :: Python :: 3.7
Classifier: Programming Language :: Python :: 3.8
Classifier: Programming Language :: Python :: 3.9
Classifier: Topic :: Software Development :: Libraries :: Python Modules
Requires-Python: !=3.0.*,!=3.1.*,!=3.2.*,!=3.3.*,!=3.4.*,>=2.7
License-File: LICENSE
Requires-Dist: dnspython (>=1.15.0)
Requires-Dist: idna (>=2.0.0)
